{
  "kind": "ReplicationController",
  "apiVersion": "v1beta3",
  "metadata": {
    "name": "inaetics-processor-celix-controller",
    "creationTimestamp": null,
    "labels": {
      "name": "inaetics-processor-celix-controller"
    }
  },
  "spec": {
    "replicas": 1,
    "selector": {
      "name": "inaetics-processor-celix-pod"
    },
    "template": {
      "metadata": {
        "creationTimestamp": null,
        "labels": {
          "name": "inaetics-processor-celix-pod"
        }
      },
      "spec": {
        "volumes": null,
        "containers": [
          {
            "name": "inaetics-processor-celix-container",
            "image": "inaetics/celix-agent",
            "args": [
              "/tmp/node-agent.sh",
              "celix_3"
            ],
            "ports": [
              {
                "hostPort": 9082,
                "containerPort": 8080,
                "protocol": "TCP"
              }
            ],
            "env": [
              {
                "name": "ETCDCTL_PEERS",
                "value": "172.17.8.20:4001"
              },
              {
                "name": "HOSTPORT",
                "value": "8080"
              }
            ],
            "resources": {},
            "terminationMessagePath": "/dev/termination-log",
            "imagePullPolicy": "IfNotPresent",
            "capabilities": {}
          }
        ],
        "restartPolicy": "Always",
        "dnsPolicy": "ClusterFirst"
      }
    }
  },
  "status": {
    "replicas": 0
  }
}
